setup.py
sams_dsnd_probability/Binomialdistribution.py
sams_dsnd_probability/Binomialdistribution_challenge.py
sams_dsnd_probability/Gaussiandistribution.py
sams_dsnd_probability/Generaldistribution.py
sams_dsnd_probability/__init__.py
sams_dsnd_probability.egg-info/PKG-INFO
sams_dsnd_probability.egg-info/SOURCES.txt
sams_dsnd_probability.egg-info/dependency_links.txt
sams_dsnd_probability.egg-info/not-zip-safe
sams_dsnd_probability.egg-info/top_level.txt