Metadata-Version: 2.1
Name: sams-dsnd-probability
Version: 1.2
Summary: Gaussian and Binomial distribution
Author-email: ajayisamuelofficial@gmail.com
